gherkin_translator/__init__.py
gherkin_translator/__main__.py
gherkin_translator/py.typed
gherkin_translator/translator.py
gherkin_translator-1.0.1.dist-info/METADATA
gherkin_translator-1.0.1.dist-info/WHEEL
gherkin_translator-1.0.1.dist-info/top_level.txt
gherkin_translator-1.0.1.dist-info/RECORD
