Metadata-Version: 2.1
Name: gherkin-translator
Version: 1.0.1
Summary: Транслятор ключевых слов пользовательского сценария из русского языка в английский
Home-page: https://github.com/Gwinkamp/gherkin-translator.git
Author: Gwinkamp
Author-email: Aleksey-Y-Kiryutin@yandex.ru
Keywords: tools
Classifier: Topic :: Utilities
Requires-Python: >=3.10
Requires-Dist: typer >=0.9.0
